Workbook

Sheet Assumptions
A1: TCS 3-Statement Financial Model
A2: Currency: INR Crores | Fiscal year ending March 31 | 2 years actual + 5 years forecast
A4: Period | B4: FY25A | C4: FY26A | D4: FY27E | E4: FY28E | F4: FY29E | G4: FY30E | H4: FY31E
A5: Status | B5: Actual | C5: Actual | D5: Forecast | E5: Forecast | F5: Forecast | G5: Forecast | H5: Forecast
A7: Historical Inputs
A8: Revenue from operations | B8: 255324 | C8: 267021
A9: Operating expenses excl. D&A | B9: 187917 | C9: 194623
A10: Depreciation & amortization | B10: 5242 | C10: 5560
A11: Other income | B11: 3962 | C11: 4402
A12: Finance cost | B12: 796 | C12: 1227
A13: Exceptional items | B13: 0 | C13: 4526
A14: Tax expense | B14: 16534 | C14: 16033
A15: Net income / PAT | B15: 48797 | C15: 49454
A16: Cash & bank balances | B16: 15463 | C16: 12908
A17: Current investments | B17: 30964 | C17: 33988
A18: Trade receivables | B18: 59046 | C18: 67714
A19: Other current assets | B19: 17396 | C19: 21095
... A27: Other equity & NCI | B27: 95266 | C27: 108116
A29: Forecast Assumptions
A30: Revenue growth | D30: 0.05 | E30: 0.06 | F30: 0.06 | G30: 0.055 | H30: 0.05
A31: EBITDA margin | D31: 0.272 | E31: 0.275 | F31: 0.278 | G31: 0.28 | H31: 0.28
A32: D&A % of revenue | D32: 0.021 | E32: 0.021 | F32: 0.021 | G32: 0.021 | H32: 0.021
A33: Other income % of revenue | D33: 0.016 | E33: 0.015 | F33: 0.015 | G33: 0.014 | H33: 0.014
A34: Finance cost % of revenue | D34: 0.0045 | E34: 0.0045 | F34: 0.0045 | G34: 0.0045 | H34: 0.0045
A35: Tax rate | D35: 0.25 | E35: 0.25 | F35: 0.25 | G35: 0.25 | H35: 0.25
A36: Dividend payout % of net income | D36: 0.8 | E36: 0.8 | F36: 0.8 | G36: 0.8 | H36: 0.8
A37: Cash & bank balances % of revenue | D37: 0.048 | E37: 0.048 | F37: 0.048 | G37: 0.048 | H37: 0.048
A38: Receivable days | D38: 93 | E38: 93 | F38: 92 | G38: 92 | H38: 92
A39: Other current assets % of revenue | D39: 0.079 | E39: 0.079 | F39: 0.078 | G39: 0.078 | H39: 0.078
A40: PP&E / ROU assets % of revenue | D40: 0.05 | E40: 0.05 | F40: 0.05 | G40: 0.05 | H40: 0.05
A41: Goodwill & intangibles % of revenue | D41: 0.035 | E41: 0.033 | F41: 0.031 | G41: 0.03 | H41: 0.03
... A45: Other non-current liabilities % of revenue | D45: 0.049 | E45: 0.049 | F45: 0.048 | G45: 0.048 | H45: 0.048
A47: Historical Cash Flow Inputs
A48: Beginning cash & bank balances | B48: 13286 | C48: 15463
A49: Cash from operating activities | B49: 48908 | C49: 52094
A50: Capital expenditure | B50: -3861 | C50: -4037
A51: Dividends paid | B51: -44860 | C51: -39440
A52: Ending cash & bank balances | B52: 15463 | C52: 12908

Sheet Income Statement
A1: TCS Income Statement
A2: INR Crores, fiscal year ending March 31
A4: Period | B4: FY25A | C4: FY26A | D4: FY27E | E4: FY28E | F4: FY29E | G4: FY30E | H4: FY31E
A5: Status | B5: Actual | C5: Actual | D5: Forecast | E5: Forecast | F5: Forecast | G5: Forecast | H5: Forecast
A7: Revenue from operations | B7: =Assumptions!B8 -> 255324 | C7: =Assumptions!C8 -> 267021 | D7: =C7*(1+Assumptions!D30) -> 280372.05 | E7: =D7*(1+Assumptions!E30) -> 297194.37 | F7: =E7*(1+Assumptions!F30) -> 315026.04 | G7: =F7*(1+Assumptions!G30) -> 332352.47 | H7: =G7*(1+Assumptions!H30) -> 348970.09
A8: Revenue growth | B8: n.m. | C8: =C7/B7-1 -> 0.04581238 | D8: =D7/C7-1 -> 0.05 | E8: =E7/D7-1 -> 0.06 | F8: =F7/E7-1 -> 0.06 | G8: =G7/F7-1 -> 0.055 | H8: =H7/G7-1 -> 0.05
A9: Operating expenses excl. D&A | B9: =Assumptions!B9 -> 187917 | C9: =Assumptions!C9 -> 194623 | D9: =D7*(1-Assumptions!D31) -> 204110.85 | E9: =E7*(1-Assumptions!E31) -> 215465.92 | F9: =F7*(1-Assumptions!F31) -> 227448.8 | G9: =G7*(1-Assumptions!G31) -> 239293.78 | H9: =H7*(1-Assumptions!H31) -> 251258.47
A10: EBITDA | B10: =B7-B9 -> 67407 | C10: =C7-C9 -> 72398 | D10: =D7-D9 -> 76261.198 | E10: =E7-E9 -> 81728.453 | F10: =F7-F9 -> 87577.238 | G10: =G7-G9 -> 93058.691 | H10: =H7-H9 -> 97711.625
A11: EBITDA margin | B11: =B10/B7 -> 0.26400573 | C11: =C10/C7 -> 0.27113223 | D11: =D10/D7 -> 0.272 | E11: =E10/E7 -> 0.275 | F11: =F10/F7 -> 0.278 | G11: =G10/G7 -> 0.28 | H11: =H10/H7 -> 0.28
A12: Depreciation & amortization | B12: =Assumptions!B10 -> 5242 | C12: =Assumptions!C10 -> 5560 | D12: =D7*Assumptions!D32 -> 5887.813 | E12: =E7*Assumptions!E32 -> 6241.0818 | F12: =F7*Assumptions!F32 -> 6615.5467 | G12: =G7*Assumptions!G32 -> 6979.4018 | H12: =H7*Assumptions!H32 -> 7328.3719
A13: EBIT | B13: =B10-B12 -> 62165 | C13: =C10-C12 -> 66838 | D13: =D10-D12 -> 70373.385 | E13: =E10-E12 -> 75487.371 | F13: =F10-F12 -> 80961.691 | G13: =G10-G12 -> 86079.289 | H13: =H10-H12 -> 90383.253
A14: EBIT margin | B14: =B13/B7 -> 0.24347496 | C14: =C13/C7 -> 0.2503099 | D14: =D13/D7 -> 0.251 | E14: =E13/E7 -> 0.254 | F14: =F13/F7 -> 0.257 | G14: =G13/G7 -> 0.259 | H14: =H13/H7 -> 0.259
A15: Other income | B15: =Assumptions!B11 -> 3962 | C15: =Assumptions!C11 -> 4402 | D15: =D7*Assumptions!D33 -> 4485.9528 | E15: =E7*Assumptions!E33 -> 4457.9156 | F15: =F7*Assumptions!F33 -> 4725.3905 | G15: =G7*Assumptions!G33 -> 4652.9345 | H15: =H7*Assumptions!H33 -> 4885.5813
A16: Finance cost | B16: =Assumptions!B12 -> 796 | C16: =Assumptions!C12 -> 1227 | D16: =D7*Assumptions!D34 -> 1261.6742 | E16: =E7*Assumptions!E34 -> 1337.3747 | F16: =F7*Assumptions!F34 -> 1417.6172 | G16: =G7*Assumptions!G34 -> 1495.5861 | H16: =H7*Assumptions!H34 -> 1570.3654
A17: Exceptional items | B17: =Assumptions!B13 -> 0 | C17: =Assumptions!C13 -> 4526 | D17: =0 -> 0 | E17: =0 -> 0 | F17: =0 -> 0 | G17: =0 -> 0 | H17: =0 -> 0
A18: Profit before tax | B18: =B13+B15-B16-B17 -> 65331 | C18: =C13+C15-C16-C17 -> 65487 | D18: =D13+D15-D16-D17 -> 73597.663 | E18: =E13+E15-E16-E17 -> 78607.912 | F18: =F13+F15-F16-F17 -> 84269.464 | G18: =G13+G15-G16-G17 -> 89236.637 | H18: =H13+H15-H16-H17 -> 93698.469
A19: Tax expense | B19: =Assumptions!B14 -> 16534 | C19: =Assumptions!C14 -> 16033 | D19: =D18*Assumptions!D35 -> 18399.416 | E19: =E18*Assumptions!E35 -> 19651.978 | F19: =F18*Assumptions!F35 -> 21067.366 | G19: =G18*Assumptions!G35 -> 22309.159 | H19: =H18*Assumptions!H35 -> 23424.617
A20: Tax rate | B20: =B19/B18 -> 0.25308047 | C20: =C19/C18 -> 0.24482722 | D20: =D19/D18 -> 0.25 | E20: =E19/E18 -> 0.25 | F20: =F19/F18 -> 0.25 | G20: =G19/G18 -> 0.25 | H20: =H19/H18 -> 0.25
A21: Net income / PAT | B21: =Assumptions!B15 -> 48797 | C21: =Assumptions!C15 -> 49454 | D21: =D18-D19 -> 55198.247 | E21: =E18-E19 -> 58955.934 | F21: =F18-F19 -> 63202.098 | G21: =G18-G19 -> 66927.478 | H21: =H18-H19 -> 70273.852
A22: Net income margin | B22: =B21/B7 -> 0.19111795 | C22: =C21/C7 -> 0.18520641 | D22: =D21/D7 -> 0.196875 | E22: =E21/E7 -> 0.198375 | F22: =F21/F7 -> 0.200625 | G22: =G21/G7 -> 0.201375 | H22: =H21/H7 -> 0.201375

Sheet Balance Sheet
A1: TCS Balance Sheet
A2: INR Crores, fiscal year ending March 31
A4: Period | B4: FY25A | C4: FY26A | D4: FY27E | E4: FY28E | F4: FY29E | G4: FY30E | H4: FY31E
A5: Status | B5: Actual | C5: Actual | D5: Forecast | E5: Forecast | F5: Forecast | G5: Forecast | H5: Forecast
A7: Cash & bank balances | B7: =Assumptions!B16 -> 15463 | C7: =Assumptions!C16 -> 12908 | D7: ='Income Statement'!D7*Assumptions!D37 -> 13457.858 | E7: ='Income Statement'!E7*Assumptions!E37 -> 14265.33 | F7: ='Income Statement'!F7*Assumptions!F37 -> 15121.25 | G7: ='Income Statement'!G7*Assumptions!G37 -> 15952.918 | H7: ='Income Statement'!H7*Assumptions!H37 -> 16750.564
A8: Current investments / surplus funds | B8: =Assumptions!B17 -> 30964 | C8: =Assumptions!C17 -> 33988 | D8: =D24-(D7+D9+D10+D12+D13+D14) -> 41013.475 | E8: =E24-(E7+E9+E10+E12+E13+E14) -> 48688.801 | F8: =F24-(F7+F9+F10+F12+F13+F14) -> 57865.155 | G8: =G24-(G7+G9+G10+G12+G13+G14) -> 66848.378 | H8: =H24-(H7+H9+H10+H12+H13+H14) -> 76378.829
A9: Trade receivables | B9: =Assumptions!B18 -> 59046 | C9: =Assumptions!C18 -> 67714 | D9: ='Income Statement'!D7*Assumptions!D38/365 -> 71437.262 | E9: ='Income Statement'!E7*Assumptions!E38/365 -> 75723.498 | F9: ='Income Statement'!F7*Assumptions!F38/365 -> 79403.823 | G9: ='Income Statement'!G7*Assumptions!G38/365 -> 83771.033 | H9: ='Income Statement'!H7*Assumptions!H38/365 -> 87959.585
A10: Other current assets | B10: =Assumptions!B19 -> 17396 | C10: =Assumptions!C19 -> 21095 | D10: ='Income Statement'!D7*Assumptions!D39 -> 22149.392 | E10: ='Income Statement'!E7*Assumptions!E39 -> 23478.355 | F10: ='Income Statement'!F7*Assumptions!F39 -> 24572.031 | G10: ='Income Statement'!G7*Assumptions!G39 -> 25923.492 | H10: ='Income Statement'!H7*Assumptions!H39 -> 27219.667
A11: Total current assets | B11: =SUM(B7:B10) -> 122869 | C11: =SUM(C7:C10) -> 135705 | D11: =SUM(D7:D10) -> 148057.99 | E11: =SUM(E7:E10) -> 162155.98 | F11: =SUM(F7:F10) -> 176962.26 | G11: =SUM(G7:G10) -> 192495.82 | H11: =SUM(H7:H10) -> 208308.65
A12: PP&E / ROU assets, net | B12: =Assumptions!B20 -> 12407 | C12: =Assumptions!C20 -> 13441 | D12: ='Income Statement'!D7*Assumptions!D40 -> 14018.603 | E12: ='Income Statement'!E7*Assumptions!E40 -> 14859.719 | F12: ='Income Statement'!F7*Assumptions!F40 -> 15751.302 | G12: ='Income Statement'!G7*Assumptions!G40 -> 16617.623 | H12: ='Income Statement'!H7*Assumptions!H40 -> 17448.505
A13: Goodwill & intangibles | B13: =Assumptions!B21 -> 2800 | C13: =Assumptions!C21 -> 9284 | D13: ='Income Statement'!D7*Assumptions!D41 -> 9813.0217 | E13: ='Income Statement'!E7*Assumptions!E41 -> 9807.4143 | F13: ='Income Statement'!F7*Assumptions!F41 -> 9765.8071 | G13: ='Income Statement'!G7*Assumptions!G41 -> 9970.574 | H13: ='Income Statement'!H7*Assumptions!H41 -> 10469.103
A14: Other non-current assets | B14: =Assumptions!B22 -> 21410 | C14: =Assumptions!C22 -> 23942 | D14: ='Income Statement'!D7*Assumptions!D42 -> 25233.484 | E14: ='Income Statement'!E7*Assumptions!E42 -> 26450.299 | F14: ='Income Statement'!F7*Assumptions!F42 -> 27722.291 | G14: ='Income Statement'!G7*Assumptions!G42 -> 28914.665 | H14: ='Income Statement'!H7*Assumptions!H42 -> 30360.398
A15: Total assets | B15: =SUM(B11:B14) -> 159486 | C15: =SUM(C11:C14) -> 182372 | D15: =SUM(D11:D14) -> 197123.1 | E15: =SUM(E11:E14) -> 213273.42 | F15: =SUM(F11:F14) -> 230201.66 | G15: =SUM(G11:G14) -> 247998.68 | H15: =SUM(H11:H14) -> 266586.65
A16: Trade payables | B16: =Assumptions!B23 -> 13909 | C16: =Assumptions!C23 -> 14808 | D16: ='Income Statement'!D7*Assumptions!D43/365 -> 15362.852 | E16: ='Income Statement'!E7*Assumptions!E43/365 -> 16284.623 | F16: ='Income Statement'!F7*Assumptions!F43/365 -> 17261.701 | G16: ='Income Statement'!G7*Assumptions!G43/365 -> 18211.094 | H16: ='Income Statement'!H7*Assumptions!H43/365 -> 19121.649
A17: Other current liabilities | B17: =Assumptions!B24 -> 39092 | C17: =Assumptions!C24 -> 46106 | D17: ='Income Statement'!D7*Assumptions!D44 -> 48504.365 | E17: ='Income Statement'!E7*Assumptions!E44 -> 51117.432 | F17: ='Income Statement'!F7*Assumptions!F44 -> 53869.452 | G17: ='Income Statement'!G7*Assumptions!G44 -> 56499.919 | H17: ='Income Statement'!H7*Assumptions!H44 -> 59324.915
A18: Total current liabilities | B18: =SUM(B16:B17) -> 53001 | C18: =SUM(C16:C17) -> 60914 | D18: =SUM(D16:D17) -> 63867.217 | E18: =SUM(E16:E17) -> 67402.055 | F18: =SUM(F16:F17) -> 71131.153 | G18: =SUM(G16:G17) -> 74711.014 | H18: =SUM(H16:H17) -> 78446.564
A19: Other non-current liabilities | B19: =Assumptions!B25 -> 10857 | C19: =Assumptions!C25 -> 12980 | D19: ='Income Statement'!D7*Assumptions!D45 -> 13738.23 | E19: ='Income Statement'!E7*Assumptions!E45 -> 14562.524 | F19: ='Income Statement'!F7*Assumptions!F45 -> 15121.25 | G19: ='Income Statement'!G7*Assumptions!G45 -> 15952.918 | H19: ='Income Statement'!H7*Assumptions!H45 -> 16750.564
A20: Total liabilities | B20: =SUM(B18:B19) -> 63858 | C20: =SUM(C18:C19) -> 73894 | D20: =SUM(D18:D19) -> 77605.447 | E20: =SUM(E18:E19) -> 81964.58 | F20: =SUM(F18:F19) -> 86252.402 | G20: =SUM(G18:G19) -> 90663.932 | H20: =SUM(H18:H19) -> 95197.129
A21: Share capital | B21: =Assumptions!B26 -> 362 | C21: =Assumptions!C26 -> 362 | D21: =C21 -> 362 | E21: =D21 -> 362 | F21: =E21 -> 362 | G21: =F21 -> 362 | H21: =G21 -> 362
A22: Other equity & NCI | B22: =Assumptions!B27 -> 95266 | C22: =Assumptions!C27 -> 108116 | D22: =C22+'Income Statement'!D21-(-'Cash Flow'!D14) -> 119155.65 | E22: =D22+'Income Statement'!E21-(-'Cash Flow'!E14) -> 130946.84 | F22: =E22+'Income Statement'!F21-(-'Cash Flow'!F14) -> 143587.26 | G22: =F22+'Income Statement'!G21-(-'Cash Flow'!G14) -> 156972.75 | H22: =G22+'Income Statement'!H21-(-'Cash Flow'!H14) -> 171027.52
A23: Total equity | B23: =SUM(B21:B22) -> 95628 | C23: =SUM(C21:C22) -> 108478 | D23: =SUM(D21:D22) -> 119517.65 | E23: =SUM(E21:E22) -> 131308.84 | F23: =SUM(F21:F22) -> 143949.26 | G23: =SUM(G21:G22) -> 157334.75 | H23: =SUM(H21:H22) -> 171389.52
A24: Total liabilities & equity | B24: =B20+B23 -> 159486 | C24: =C20+C23 -> 182372 | D24: =D20+D23 -> 197123.1 | E24: =E20+E23 -> 213273.42 | F24: =F20+F23 -> 230201.66 | G24: =G20+G23 -> 247998.68 | H24: =H20+H23 -> 266586.65
A25: Balance check | B25: =B15-B24 -> 0 | C25: =C15-C24 -> 0 | D25: =D15-D24 -> 0 | E25: =E15-E24 -> 0 | F25: =F15-F24 -> 0 | G25: =G15-G24 -> 0 | H25: =H15-H24 -> 0

Sheet Cash Flow
A1: TCS Cash Flow Statement
A2: INR Crores, fiscal year ending March 31
A4: Period | B4: FY25A | C4: FY26A | D4: FY27E | E4: FY28E | F4: FY29E | G4: FY30E | H4: FY31E
A5: Status | B5: Actual | C5: Actual | D5: Forecast | E5: Forecast | F5: Forecast | G5: Forecast | H5: Forecast
A7: Beginning cash & bank balances | B7: =Assumptions!B48 -> 13286 | C7: =Assumptions!C48 -> 15463 | D7: =C17 -> 12908 | E7: =D17 -> 13457.858 | F7: =E17 -> 14265.33 | G7: =F17 -> 15121.25 | H7: =G17 -> 15952.918
A8: Net income / PAT | B8: ='Income Statement'!B21 -> 48797 | C8: ='Income Statement'!C21 -> 49454 | D8: ='Income Statement'!D21 -> 55198.247 | E8: ='Income Statement'!E21 -> 58955.934 | F8: ='Income Statement'!F21 -> 63202.098 | G8: ='Income Statement'!G21 -> 66927.478 | H8: ='Income Statement'!H21 -> 70273.852
A9: Depreciation & amortization | B9: ='Income Statement'!B12 -> 5242 | C9: ='Income Statement'!C12 -> 5560 | D9: ='Income Statement'!D12 -> 5887.813 | E9: ='Income Statement'!E12 -> 6241.0818 | F9: ='Income Statement'!F12 -> 6615.5467 | G9: ='Income Statement'!G12 -> 6979.4018 | H9: ='Income Statement'!H12 -> 7328.3719
A10: Working capital & other operating items | B10: =Assumptions!B49-B8-B9 -> -5131 | C10: =Assumptions!C49-C8-C9 -> -2920 | D10: =-(('Balance Sheet'!D9+'Balance Sheet'!D10-'Balance Sheet'!D16-'Balance Sheet'!D17)-('Balance Sheet'!C9+'Balance Sheet'!C10-'Balance Sheet'!C16-'Balance Sheet'!C17)) -> -1824.4373 | E10: =-(('Balance Sheet'!E9+'Balance Sheet'!E10-'Balance Sheet'!E16-'Balance Sheet'!E17)-('Balance Sheet'!D9+'Balance Sheet'!D10-'Balance Sheet'!D16-'Balance Sheet'!D17)) -> -2080.3606 | F10: =-(('Balance Sheet'!F9+'Balance Sheet'!F10-'Balance Sheet'!F16-'Balance Sheet'!F17)-('Balance Sheet'!E9+'Balance Sheet'!E10-'Balance Sheet'!E16-'Balance Sheet'!E17)) -> -1044.9028 | G10: =-(('Balance Sheet'!G9+'Balance Sheet'!G10-'Balance Sheet'!G16-'Balance Sheet'!G17)-('Balance Sheet'!F9+'Balance Sheet'!F10-'Balance Sheet'!F16-'Balance Sheet'!F17)) -> -2138.811 | H10: =-(('Balance Sheet'!H9+'Balance Sheet'!H10-'Balance Sheet'!H16-'Balance Sheet'!H17)-('Balance Sheet'!G9+'Balance Sheet'!G10-'Balance Sheet'!G16-'Balance Sheet'!G17)) -> -1749.1756
A11: Cash from operating activities | B11: =Assumptions!B49 -> 48908 | C11: =Assumptions!C49 -> 52094 | D11: =SUM(D8:D10) -> 59261.623 | E11: =SUM(E8:E10) -> 63116.655 | F11: =SUM(F8:F10) -> 68772.742 | G11: =SUM(G8:G10) -> 71768.069 | H11: =SUM(H8:H10) -> 75853.048
A12: Capital expenditure | B12: =Assumptions!B50 -> -3861 | C12: =Assumptions!C50 -> -4037 | D12: =-('Balance Sheet'!D12-'Balance Sheet'!C12+D9) -> -6465.4156 | E12: =-('Balance Sheet'!E12-'Balance Sheet'!D12+E9) -> -7082.198 | F12: =-('Balance Sheet'!F12-'Balance Sheet'!E12+F9) -> -7507.1299 | G12: =-('Balance Sheet'!G12-'Balance Sheet'!F12+G9) -> -7845.7234 | H12: =-('Balance Sheet'!H12-'Balance Sheet'!G12+H9) -> -8159.2531
A13: Free cash flow | B13: =B11+B12 -> 45047 | C13: =C11+C12 -> 48057 | D13: =D11+D12 -> 52796.208 | E13: =E11+E12 -> 56034.457 | F13: =F11+F12 -> 61265.612 | G13: =G11+G12 -> 63922.346 | H13: =H11+H12 -> 67693.795
A14: Dividends paid | B14: =Assumptions!B51 -> -44860 | C14: =Assumptions!C51 -> -39440 | D14: =-D8*Assumptions!D36 -> -44158.598 | E14: =-E8*Assumptions!E36 -> -47164.747 | F14: =-F8*Assumptions!F36 -> -50561.679 | G14: =-G8*Assumptions!G36 -> -53541.982 | H14: =-H8*Assumptions!H36 -> -56219.082
A15: Net investments / other financing | B15: =B17-B7-B11-B12-B14 -> 1990 | C15: =C17-C7-C11-C12-C14 -> -11172 | D15: =D17-D7-D11-D12-D14 -> -8087.7513 | E15: =E17-E7-E11-E12-E14 -> -8062.2385 | F15: =F17-F7-F11-F12-F14 -> -9848.0139 | G15: =G17-G7-G11-G12-G14 -> -9548.6943 | H15: =H17-H7-H11-H12-H14 -> -10677.068
A16: Net change in cash | B16: =B11+B12+B14+B15 -> 2177 | C16: =C11+C12+C14+C15 -> -2555 | D16: =D11+D12+D14+D15 -> 549.8584 | E16: =E11+E12+E14+E15 -> 807.4715 | F16: =F11+F12+F14+F15 -> 855.91979 | G16: =G11+G12+G14+G15 -> 831.66873 | H16: =H11+H12+H14+H15 -> 797.64592
A17: Ending cash & bank balances | B17: =Assumptions!B52 -> 15463 | C17: =Assumptions!C52 -> 12908 | D17: ='Balance Sheet'!D7 -> 13457.858 | E17: ='Balance Sheet'!E7 -> 14265.33 | F17: ='Balance Sheet'!F7 -> 15121.25 | G17: ='Balance Sheet'!G7 -> 15952.918 | H17: ='Balance Sheet'!H7 -> 16750.564
A18: Cash roll-forward check | B18: =B7+B16-B17 -> 0 | C18: =C7+C16-C17 -> 0 | D18: =D7+D16-D17 -> 0 | E18: =E7+E16-E17 -> 0 | F18: =F7+F16-F17 -> 0 | G18: =G7+G16-G17 -> 0 | H18: =H7+H16-H17 -> 0

Sheet Checks
A1: Model Checks
A3: Check | B3: Status | C3: Delta | D3: Location
A4: Balance sheet balances | B4: {=IF(MAX(ABS('Balance Sheet'!B25:H25))<1,"PASS","FAIL")} -> PASS | C4: {=MAX(ABS('Balance Sheet'!B25:H25))} -> 0 | D4: Balance Sheet!B25:H25
A5: Cash roll-forward ties | B5: {=IF(MAX(ABS('Cash Flow'!B18:H18))<1,"PASS","FAIL")} -> PASS | C5: {=MAX(ABS('Cash Flow'!B18:H18))} -> 0 | D5: Cash Flow!B18:H18
A7: Note | B7: Current investments / surplus funds is the balancing asset in forecast years to avoid circularity while cash and retained earnings remain linked.

Sheet Sources
A1: Sources & Assumptions Log
A3: Item | B3: Value | C3: Units | D3: Period / As-of | E3: Source Name | F3: Ref | G3: Notes | H3: Accessed | I3: Model Location
A4: Revenue from operations | B4: 267021 | C4: INR Cr | D4: FY26 | E4: TCS Annual Report 2025-26 | F4: Financial highlights | G4: Actual revenue; FY25 also sourced from same table | H4: 46188 | I4: Assumptions!B8:C8
A5: EBIT / operating profit | B5: 66838 | C5: INR Cr | D5: FY26 | E5: TCS Annual Report / public financial data | F5: Profitability / operating profit | G5: Used with EBITDA to derive simplified D&A | H5: 46188 | I5: Income Statement!B13:C13
A6: Balance sheet categories | B6: 182372 | C6: INR Cr | D6: FY26 | E6: Public consolidated balance sheet data | F6: Total assets / total equity | G6: Used to cross-check simplified BS categories | H6: 46188 | I6: Balance Sheet!B7:C25
A7: Cash flow actuals | B7: 52094 | C7: INR Cr | D7: FY26 | E7: Public consolidated cash flow data | F7: Cash from operating activities | G7: Simplified CFS uses CFO, capex and dividends | H7: 46188 | I7: Cash Flow!B7:C18
A8: Forecast assumptions | B8: Base case | C8: n/a | D8: FY27E-FY31E | E8: Analyst assumption | F8: Base case | G8: Editable forecast drivers in blue | H8: 46188 | I8: Assumptions!D30:H45
